{
  "generator-jhipster": {
    "promptValues": {
      "packageName": "com.smilyk"
    },
    "jhipsterVersion": "6.10.5",
    "applicationType": "monolith",
    "baseName": "rfbloyalty",
    "packageName": "com.smilyk",
    "packageFolder": "com/smilyk",
    "serverPort": "8080",
    "authenticationType": "session",
    "cacheProvider": "ehcache",
    "enableHibernateCache": true,
    "websocket": false,
    "databaseType": "sql",
    "devDatabaseType": "h2Memory",
    "prodDatabaseType": "mysql",
    "searchEngine": false,
    "messageBroker": false,
    "serviceDiscoveryType": false,
    "buildTool": "gradle",
    "enableSwaggerCodegen": false,
    "rememberMeKey": "c49c447bbd5f6ef31a212c6b28556d123b19a88772792346f3213bff18a757f09ce1ee258326586d7710c0f0bf47acf15e32",
    "embeddableLaunchScript": false,
    "useSass": true,
    "clientPackageManager": "npm",
    "clientFramework": "angularX",
    "clientTheme": "none",
    "clientThemeVariant": "",
    "creationTimestamp": 1613643539165,
    "testFrameworks": [],
    "jhiPrefix": "jhi",
    "entitySuffix": "",
    "dtoSuffix": "DTO",
    "otherModules": [],
    "enableTranslation": false,
    "blueprints": []
  }
}
